py_riff/__init__.py
py_riff/commons.py
py_riff-1.7.dist-info/LICENSE
py_riff-1.7.dist-info/METADATA
py_riff-1.7.dist-info/WHEEL
py_riff-1.7.dist-info/top_level.txt
py_riff-1.7.dist-info/RECORD
